aiohttp_datadog/__init__.py
aiohttp_datadog-0.5.0.dist-info/LICENSE
aiohttp_datadog-0.5.0.dist-info/METADATA
aiohttp_datadog-0.5.0.dist-info/WHEEL
aiohttp_datadog-0.5.0.dist-info/top_level.txt
aiohttp_datadog-0.5.0.dist-info/RECORD
